dj_impediments/__init__.py
dj_impediments/cache.py
dj_impediments/models.py
dj_impediments/tests.py
dj_impediments/conf/__init__.py
dj_impediments/conf/defaults.py
django_gddkia_impediments_on_roads-0.1.1.dist-info/DESCRIPTION.rst
django_gddkia_impediments_on_roads-0.1.1.dist-info/METADATA
django_gddkia_impediments_on_roads-0.1.1.dist-info/RECORD
django_gddkia_impediments_on_roads-0.1.1.dist-info/WHEEL
django_gddkia_impediments_on_roads-0.1.1.dist-info/metadata.json
django_gddkia_impediments_on_roads-0.1.1.dist-info/top_level.txt
tests/__init__.py
tests/runtests.py
tests/test_settings.py
